oorl/__init__.py
oorl-0.0.1.dist-info/METADATA
oorl-0.0.1.dist-info/WHEEL
oorl-0.0.1.dist-info/RECORD
